a2h/__init__.py
a2h-0.1.dev0.dist-info/LICENSE
a2h-0.1.dev0.dist-info/METADATA
a2h-0.1.dev0.dist-info/WHEEL
a2h-0.1.dev0.dist-info/top_level.txt
a2h-0.1.dev0.dist-info/RECORD
